flextrees/__init__.py
flextrees/datasets/__init__.py
flextrees/datasets/preprocessing_utils.py
flextrees/datasets/tabular_datasets.py
flextrees/pool/__init__.py
flextrees/pool/aggregators_fedid3.py
flextrees/pool/aggregators_fedrf.py
flextrees/pool/aggregators_fegbdt.py
flextrees/pool/pool_functions.py
flextrees/pool/primitives_fedgbdt.py
flextrees/pool/primitives_fedid3.py
flextrees/pool/primitives_fedrf.py
flextrees/utils/__init__.py
flextrees/utils/trees_metrics.py
flextrees/utils/utils_gbdt.py
flextrees/utils/utils_rf.py
flextrees/utils/utils_trees.py
flextrees-0.1.0.dist-info/LICENSE
flextrees-0.1.0.dist-info/METADATA
flextrees-0.1.0.dist-info/WHEEL
flextrees-0.1.0.dist-info/top_level.txt
flextrees-0.1.0.dist-info/RECORD
