Metadata-Version: 2.1
Name: flextrees
Version: 0.1.0
Author: Alberto Argente-Garrido
Keywords: decision-trees explainable FL federated-learning flexible
License-File: LICENSE
Requires-Dist: flex
Requires-Dist: numpy
Requires-Dist: bitarray
Requires-Dist: ucimlrepo
Requires-Dist: future
